README.txt
setup.cfg
setup.py
collective/__init__.py
collective.externalsnippet.egg-info/PKG-INFO
collective.externalsnippet.egg-info/SOURCES.txt
collective.externalsnippet.egg-info/dependency_links.txt
collective.externalsnippet.egg-info/entry_points.txt
collective.externalsnippet.egg-info/namespace_packages.txt
collective.externalsnippet.egg-info/not-zip-safe
collective.externalsnippet.egg-info/requires.txt
collective.externalsnippet.egg-info/top_level.txt
collective/externalsnippet/README.txt
collective/externalsnippet/__init__.py
collective/externalsnippet/configure.zcml
collective/externalsnippet/extender.py
collective/externalsnippet/interfaces.py
collective/externalsnippet/tests.py
collective/externalsnippet/update_i18n.sh
collective/externalsnippet/viewlet.py
collective/externalsnippet/window.pt
collective/externalsnippet/locales/collective.externalsnippet.pot
collective/externalsnippet/locales/cs/LC_MESSAGES/collective.externalsnippet.po
collective/externalsnippet/locales/en/LC_MESSAGES/collective.externalsnippet.po
collective/externalsnippet/profiles/default/browserlayer.xml
collective/externalsnippet/profiles/default/metadata.xml
docs/HISTORY.txt
docs/INSTALL.txt
docs/LICENSE.GPL
docs/LICENSE.txt