Metadata-Version: 1.0
Name: collective.externalsnippet
Version: 0.2
Summary: Extends plone content with ability to render external content in viewlet.
Home-page: http://svn.plone.org/svn/collective/
Author: Lukas Zdych
Author-email: lukas.zdych@gmail.com
License: GPL
Keywords: plone external content
Platform: UNKNOWN
Classifier: Framework :: Plone
Classifier: Programming Language :: Python
